vut/__init__.py
vut/base.py
vut/config.py
vut/cuda.py
vut/io.py
vut/logger.py
vut/mapping.py
vut/palette.py
vut/rich.py
vut/time.py
vut/trainer.py
vut/util.py
vut/visualization.py
vut/visualize.py
vut/dataset/__init__.py
vut/dataset/base.py
vut/dataset/noop.py
vut/models/__init__.py
vut/models/i3d.py
vut/video/__init__.py
vut/video/reader.py
vut/video/writer.py
vut-0.1.15.dist-info/licenses/LICENSE
vut-0.1.15.dist-info/METADATA
vut-0.1.15.dist-info/WHEEL
vut-0.1.15.dist-info/top_level.txt
vut-0.1.15.dist-info/RECORD
