Metadata-Version: 2.4
Name: vut
Version: 0.1.15
Summary: Toolkit for Video Understanding tasks
Author-email: kage1020 <contact@kage1020.com>
License-Expression: MIT
Project-URL: Repository, https://github.com/kage1020/vut.git
Keywords: video,computer vision,deep learning,action recognition,action detection,action localization,action segmentation,video classification,video segmentation,video generation,video captioning,video retrieval,video understanding,video analysis,video processing
Requires-Python: >=3.12
License-File: LICENSE
Provides-Extra: full
Requires-Dist: einops>=0.8.1; extra == "full"
Requires-Dist: ffmpeg-python>=0.2.0; extra == "full"
Requires-Dist: hydra-core>=1.3.2; extra == "full"
Requires-Dist: ipywidgets>=8.1.7; extra == "full"
Requires-Dist: jaxtyping>=0.3.5; extra == "full"
Requires-Dist: matplotlib>=3.10.3; extra == "full"
Requires-Dist: numpy>=2.2.5; extra == "full"
Requires-Dist: opencv-contrib-python>=4.11.0.86; extra == "full"
Requires-Dist: opencv-python>=4.11.0.86; extra == "full"
Requires-Dist: pillow>=11.2.1; extra == "full"
Requires-Dist: polars>=1.29.0; extra == "full"
Requires-Dist: python-dotenv>=1.1.0; extra == "full"
Requires-Dist: pyyaml>=6.0.2; extra == "full"
Requires-Dist: rich>=14.0.0; extra == "full"
Requires-Dist: scikit-learn>=1.6.1; extra == "full"
Requires-Dist: torch>=2.6.0; extra == "full"
Requires-Dist: torchvision>=0.22.0; extra == "full"
Dynamic: license-file
